odoo/addons/pricelist_by_category_qty/README.rst
odoo/addons/pricelist_by_category_qty/__init__.py
odoo/addons/pricelist_by_category_qty/__manifest__.py
odoo/addons/pricelist_by_category_qty/i18n/fr.po
odoo/addons/pricelist_by_category_qty/i18n/pricelist_by_category_qty.pot
odoo/addons/pricelist_by_category_qty/models/__init__.py
odoo/addons/pricelist_by_category_qty/models/sale.py
odoo/addons/pricelist_by_category_qty/readme/CONTRIBUTORS.rst
odoo/addons/pricelist_by_category_qty/readme/DESCRIPTION.rst
odoo/addons/pricelist_by_category_qty/readme/ROADMAP.rst
odoo/addons/pricelist_by_category_qty/static/description/icon.png
odoo/addons/pricelist_by_category_qty/static/description/index.html
odoo/addons/pricelist_by_category_qty/views/sale_view.xml
odoo12_addon_pricelist_by_category_qty-12.0.1.0.0.99.dev3.dist-info/METADATA
odoo12_addon_pricelist_by_category_qty-12.0.1.0.0.99.dev3.dist-info/WHEEL
odoo12_addon_pricelist_by_category_qty-12.0.1.0.0.99.dev3.dist-info/top_level.txt
odoo12_addon_pricelist_by_category_qty-12.0.1.0.0.99.dev3.dist-info/RECORD
